jmdexcel/__init__.py
jmdexcel/insert.py
jmdexcel/select.py
jmdexcel-0.1.0.dist-info/METADATA
jmdexcel-0.1.0.dist-info/WHEEL
jmdexcel-0.1.0.dist-info/RECORD
